karlo_py-1.0.1.dist-info/METADATA
karlo_py-1.0.1.dist-info/WHEEL
karlo_py/__init__.py
karlo_py/karlo_py.cp311-win_amd64.pyd
karlo_py-1.0.1.dist-info/RECORD
