Metadata-Version: 2.1
Name: karlo_py
Version: 1.0.1
Classifier: Programming Language :: Rust
Classifier: Programming Language :: Python :: Implementation :: CPython
Classifier: Programming Language :: Python :: Implementation :: PyPy
Summary: Kakao's Karlo API Python wrapper
Author: Seok Won <ikr@kakao.com>
Author-email: Seok Won <ikr@kakao.com>
License: MIT
Requires-Python: >=3.7
